Metadata-Version: 1.0
Name: gpuastro
Version: 0.2.dev0
Summary: A GPU accelerated astrophysics library
Home-page: https://github.com/samgill844
Author: Gill, S.
Author-email: s.gill@keele.ac.uk
License: GNU
Keywords: GPU,numba,astrophysics
Platform: UNKNOWN
